finfactory/__init__.py
finfactory/_pkg_info.py
finfactory/config.py
finfactory/install_check.py
finfactory/load_his_data.py
finfactory/findata/__init__.py
finfactory/findata/api.py
finfactory/finplot/__init__.py
finfactory/finplot/_mpfold.py
finfactory/finplot/_plot_candle_deprecated.py
finfactory/finplot/finplot.py
finfactory/finplot/plot_candle.py
finfactory/fintools/__init__.py
finfactory/fintools/_backtest_timselection.py
finfactory/fintools/_copy_line.py
finfactory/fintools/_utils.py
finfactory/fintools/fintools.py
finfactory/fintools/fq.py
finfactory/fintools/fundnet.py
finfactory/fintools/options.py
finfactory/fintools/pytalib.py
finfactory/fintools/tafactor.py
finfactory/fintools/utils_chn.py
finfactory/fintools/utils_gains.py
finfactory/utils/__init__.py
finfactory/utils/utils.py
finfactory/utils/utils_crypto.py
finfactory-0.1.27.dist-info/LICENSE
finfactory-0.1.27.dist-info/METADATA
finfactory-0.1.27.dist-info/WHEEL
finfactory-0.1.27.dist-info/top_level.txt
finfactory-0.1.27.dist-info/RECORD
