Metadata-Version: 2.1
Name: finfactory
Version: 0.1.27
Summary: FinFactory is a financial toolbox.
Home-page: https://github.com/Genlovy-Hoo/finfactory/
Author: Genlovy Hoo, YueYong Hu
Author-email: genlovhyy@163.com
License: MIT
Platform: any
License-File: LICENSE
